<?xml version="1.0" encoding="UTF-8"?>
<RailMonitor>
  <Settings IP="192.168.0.243" Varlist="..\..\ATLG\VARLIST.csv" Task="500" Timeout="1000"></Settings>
<LogResource Name="IK_F-CanEmgcyMsg" Bild="pictures\trampng.png">
    <LogItem ID="0" Titel="IK_F.auiEmcyNodesCAN1_0                 IK_F_T;" Name="IK_F.auiEmcyNodesCAN1_0" POU="" Einheit="UINT" Faktor="1" Offset="0"></LogItem>
    <LogItem ID="1" Titel="IK_F.auiEmcyNodesCAN1_1                 IK_F_T;" Name="IK_F.auiEmcyNodesCAN1_1" POU="" Einheit="UINT" Faktor="1" Offset="0"></LogItem>
    <LogItem ID="2" Titel="IK_F.auiEmcyNodesCAN1_2                 IK_F_T;" Name="IK_F.auiEmcyNodesCAN1_2" POU="" Einheit="UINT" Faktor="1" Offset="0"></LogItem>
    <LogItem ID="3" Titel="IK_F.auiEmcyNodesCAN1_3                 IK_F_T;" Name="IK_F.auiEmcyNodesCAN1_3" POU="" Einheit="UINT" Faktor="1" Offset="0"></LogItem>
    <LogItem ID="4" Titel="IK_F.auiEmcyNodesCAN1_4                 IK_F_T;" Name="IK_F.auiEmcyNodesCAN1_4" POU="" Einheit="UINT" Faktor="1" Offset="0"></LogItem>
    <LogItem ID="5" Titel="IK_F.auiEmcyNodesCAN1_5                 IK_F_T;" Name="IK_F.auiEmcyNodesCAN1_5" POU="" Einheit="UINT" Faktor="1" Offset="0"></LogItem>
    <LogItem ID="6" Titel="IK_F.auiEmcyNodesCAN1_6                 IK_F_T;" Name="IK_F.auiEmcyNodesCAN1_6" POU="" Einheit="UINT" Faktor="1" Offset="0"></LogItem>
    <LogItem ID="7" Titel="IK_F.auiEmcyNodesCAN1_7                 IK_F_T;" Name="IK_F.auiEmcyNodesCAN1_7" POU="" Einheit="UINT" Faktor="1" Offset="0"></LogItem>
    <LogItem ID="8" Titel="IK_F.auiEmcyNodesCAN1_8                 IK_F_T;" Name="IK_F.auiEmcyNodesCAN1_8" POU="" Einheit="UINT" Faktor="1" Offset="0"></LogItem>
    <LogItem ID="9" Titel="IK_F.auiEmcyNodesCAN1_9                 IK_F_T;" Name="IK_F.auiEmcyNodesCAN1_9" POU="" Einheit="UINT" Faktor="1" Offset="0"></LogItem>
    <LogItem ID="10" Titel="IK_F.abEmcyMessagesCAN1_0_0             IK_F_T;" Name="IK_F.abEmcyMessagesCAN1_0_0" POU="" Einheit="BYTE" Faktor="1" Offset="0"></LogItem>
    <LogItem ID="11" Titel="IK_F.abEmcyMessagesCAN1_0_1             IK_F_T;" Name="IK_F.abEmcyMessagesCAN1_0_1" POU="" Einheit="BYTE" Faktor="1" Offset="0"></LogItem>
    <LogItem ID="12" Titel="IK_F.abEmcyMessagesCAN1_0_2             IK_F_T;" Name="IK_F.abEmcyMessagesCAN1_0_2" POU="" Einheit="BYTE" Faktor="1" Offset="0"></LogItem>
    <LogItem ID="13" Titel="IK_F.abEmcyMessagesCAN1_0_3             IK_F_T;" Name="IK_F.abEmcyMessagesCAN1_0_3" POU="" Einheit="BYTE" Faktor="1" Offset="0"></LogItem>
    <LogItem ID="14" Titel="IK_F.abEmcyMessagesCAN1_0_4             IK_F_T;" Name="IK_F.abEmcyMessagesCAN1_0_4" POU="" Einheit="BYTE" Faktor="1" Offset="0"></LogItem>
    <LogItem ID="15" Titel="IK_F.abEmcyMessagesCAN1_0_5             IK_F_T;" Name="IK_F.abEmcyMessagesCAN1_0_5" POU="" Einheit="BYTE" Faktor="1" Offset="0"></LogItem>
    <LogItem ID="16" Titel="IK_F.abEmcyMessagesCAN1_0_6             IK_F_T;" Name="IK_F.abEmcyMessagesCAN1_0_6" POU="" Einheit="BYTE" Faktor="1" Offset="0"></LogItem>
    <LogItem ID="17" Titel="IK_F.abEmcyMessagesCAN1_0_7             IK_F_T;" Name="IK_F.abEmcyMessagesCAN1_0_7" POU="" Einheit="BYTE" Faktor="1" Offset="0"></LogItem>
    <LogItem ID="18" Titel="IK_F.abEmcyMessagesCAN1_1_0             IK_F_T;" Name="IK_F.abEmcyMessagesCAN1_1_0" POU="" Einheit="BYTE" Faktor="1" Offset="0"></LogItem>
    <LogItem ID="19" Titel="IK_F.abEmcyMessagesCAN1_1_1             IK_F_T;" Name="IK_F.abEmcyMessagesCAN1_1_1" POU="" Einheit="BYTE" Faktor="1" Offset="0"></LogItem>
    <LogItem ID="20" Titel="IK_F.abEmcyMessagesCAN1_1_2             IK_F_T;" Name="IK_F.abEmcyMessagesCAN1_1_2" POU="" Einheit="BYTE" Faktor="1" Offset="0"></LogItem>
    <LogItem ID="21" Titel="IK_F.abEmcyMessagesCAN1_1_3             IK_F_T;" Name="IK_F.abEmcyMessagesCAN1_1_3" POU="" Einheit="BYTE" Faktor="1" Offset="0"></LogItem>
    <LogItem ID="22" Titel="IK_F.abEmcyMessagesCAN1_1_4             IK_F_T;" Name="IK_F.abEmcyMessagesCAN1_1_4" POU="" Einheit="BYTE" Faktor="1" Offset="0"></LogItem>
    <LogItem ID="23" Titel="IK_F.abEmcyMessagesCAN1_1_5             IK_F_T;" Name="IK_F.abEmcyMessagesCAN1_1_5" POU="" Einheit="BYTE" Faktor="1" Offset="0"></LogItem>
    <LogItem ID="24" Titel="IK_F.abEmcyMessagesCAN1_1_6             IK_F_T;" Name="IK_F.abEmcyMessagesCAN1_1_6" POU="" Einheit="BYTE" Faktor="1" Offset="0"></LogItem>
    <LogItem ID="25" Titel="IK_F.abEmcyMessagesCAN1_1_7             IK_F_T;" Name="IK_F.abEmcyMessagesCAN1_1_7" POU="" Einheit="BYTE" Faktor="1" Offset="0"></LogItem>
    <LogItem ID="26" Titel="IK_F.abEmcyMessagesCAN1_2_0             IK_F_T;" Name="IK_F.abEmcyMessagesCAN1_2_0" POU="" Einheit="BYTE" Faktor="1" Offset="0"></LogItem>
    <LogItem ID="27" Titel="IK_F.abEmcyMessagesCAN1_2_1             IK_F_T;" Name="IK_F.abEmcyMessagesCAN1_2_1" POU="" Einheit="BYTE" Faktor="1" Offset="0"></LogItem>
    <LogItem ID="28" Titel="IK_F.abEmcyMessagesCAN1_2_2             IK_F_T;" Name="IK_F.abEmcyMessagesCAN1_2_2" POU="" Einheit="BYTE" Faktor="1" Offset="0"></LogItem>
    <LogItem ID="29" Titel="IK_F.abEmcyMessagesCAN1_2_3             IK_F_T;" Name="IK_F.abEmcyMessagesCAN1_2_3" POU="" Einheit="BYTE" Faktor="1" Offset="0"></LogItem>
    <LogItem ID="30" Titel="IK_F.abEmcyMessagesCAN1_2_4             IK_F_T;" Name="IK_F.abEmcyMessagesCAN1_2_4" POU="" Einheit="BYTE" Faktor="1" Offset="0"></LogItem>
    <LogItem ID="31" Titel="IK_F.abEmcyMessagesCAN1_2_5             IK_F_T;" Name="IK_F.abEmcyMessagesCAN1_2_5" POU="" Einheit="BYTE" Faktor="1" Offset="0"></LogItem>
    <LogItem ID="32" Titel="IK_F.abEmcyMessagesCAN1_2_6             IK_F_T;" Name="IK_F.abEmcyMessagesCAN1_2_6" POU="" Einheit="BYTE" Faktor="1" Offset="0"></LogItem>
    <LogItem ID="33" Titel="IK_F.abEmcyMessagesCAN1_2_7             IK_F_T;" Name="IK_F.abEmcyMessagesCAN1_2_7" POU="" Einheit="BYTE" Faktor="1" Offset="0"></LogItem>
    <LogItem ID="34" Titel="IK_F.abEmcyMessagesCAN1_3_0             IK_F_T;" Name="IK_F.abEmcyMessagesCAN1_3_0" POU="" Einheit="BYTE" Faktor="1" Offset="0"></LogItem>
    <LogItem ID="35" Titel="IK_F.abEmcyMessagesCAN1_3_1             IK_F_T;" Name="IK_F.abEmcyMessagesCAN1_3_1" POU="" Einheit="BYTE" Faktor="1" Offset="0"></LogItem>
    <LogItem ID="36" Titel="IK_F.abEmcyMessagesCAN1_3_2             IK_F_T;" Name="IK_F.abEmcyMessagesCAN1_3_2" POU="" Einheit="BYTE" Faktor="1" Offset="0"></LogItem>
    <LogItem ID="37" Titel="IK_F.abEmcyMessagesCAN1_3_3             IK_F_T;" Name="IK_F.abEmcyMessagesCAN1_3_3" POU="" Einheit="BYTE" Faktor="1" Offset="0"></LogItem>
    <LogItem ID="38" Titel="IK_F.abEmcyMessagesCAN1_3_4             IK_F_T;" Name="IK_F.abEmcyMessagesCAN1_3_4" POU="" Einheit="BYTE" Faktor="1" Offset="0"></LogItem>
    <LogItem ID="39" Titel="IK_F.abEmcyMessagesCAN1_3_5             IK_F_T;" Name="IK_F.abEmcyMessagesCAN1_3_5" POU="" Einheit="BYTE" Faktor="1" Offset="0"></LogItem>
    <LogItem ID="40" Titel="IK_F.abEmcyMessagesCAN1_3_6             IK_F_T;" Name="IK_F.abEmcyMessagesCAN1_3_6" POU="" Einheit="BYTE" Faktor="1" Offset="0"></LogItem>
    <LogItem ID="41" Titel="IK_F.abEmcyMessagesCAN1_3_7             IK_F_T;" Name="IK_F.abEmcyMessagesCAN1_3_7" POU="" Einheit="BYTE" Faktor="1" Offset="0"></LogItem>
    <LogItem ID="42" Titel="IK_F.abEmcyMessagesCAN1_4_0             IK_F_T;" Name="IK_F.abEmcyMessagesCAN1_4_0" POU="" Einheit="BYTE" Faktor="1" Offset="0"></LogItem>
    <LogItem ID="43" Titel="IK_F.abEmcyMessagesCAN1_4_1             IK_F_T;" Name="IK_F.abEmcyMessagesCAN1_4_1" POU="" Einheit="BYTE" Faktor="1" Offset="0"></LogItem>
    <LogItem ID="44" Titel="IK_F.abEmcyMessagesCAN1_4_2             IK_F_T;" Name="IK_F.abEmcyMessagesCAN1_4_2" POU="" Einheit="BYTE" Faktor="1" Offset="0"></LogItem>
    <LogItem ID="45" Titel="IK_F.abEmcyMessagesCAN1_4_3             IK_F_T;" Name="IK_F.abEmcyMessagesCAN1_4_3" POU="" Einheit="BYTE" Faktor="1" Offset="0"></LogItem>
    <LogItem ID="46" Titel="IK_F.abEmcyMessagesCAN1_4_4             IK_F_T;" Name="IK_F.abEmcyMessagesCAN1_4_4" POU="" Einheit="BYTE" Faktor="1" Offset="0"></LogItem>
    <LogItem ID="47" Titel="IK_F.abEmcyMessagesCAN1_4_5             IK_F_T;" Name="IK_F.abEmcyMessagesCAN1_4_5" POU="" Einheit="BYTE" Faktor="1" Offset="0"></LogItem>
    <LogItem ID="48" Titel="IK_F.abEmcyMessagesCAN1_4_6             IK_F_T;" Name="IK_F.abEmcyMessagesCAN1_4_6" POU="" Einheit="BYTE" Faktor="1" Offset="0"></LogItem>
    <LogItem ID="49" Titel="IK_F.abEmcyMessagesCAN1_4_7             IK_F_T;" Name="IK_F.abEmcyMessagesCAN1_4_7" POU="" Einheit="BYTE" Faktor="1" Offset="0"></LogItem>
    <LogItem ID="50" Titel="IK_F.abEmcyMessagesCAN1_5_0             IK_F_T;" Name="IK_F.abEmcyMessagesCAN1_5_0" POU="" Einheit="BYTE" Faktor="1" Offset="0"></LogItem>
    <LogItem ID="51" Titel="IK_F.abEmcyMessagesCAN1_5_1             IK_F_T;" Name="IK_F.abEmcyMessagesCAN1_5_1" POU="" Einheit="BYTE" Faktor="1" Offset="0"></LogItem>
    <LogItem ID="52" Titel="IK_F.abEmcyMessagesCAN1_5_2             IK_F_T;" Name="IK_F.abEmcyMessagesCAN1_5_2" POU="" Einheit="BYTE" Faktor="1" Offset="0"></LogItem>
    <LogItem ID="53" Titel="IK_F.abEmcyMessagesCAN1_5_3             IK_F_T;" Name="IK_F.abEmcyMessagesCAN1_5_3" POU="" Einheit="BYTE" Faktor="1" Offset="0"></LogItem>
    <LogItem ID="54" Titel="IK_F.abEmcyMessagesCAN1_5_4             IK_F_T;" Name="IK_F.abEmcyMessagesCAN1_5_4" POU="" Einheit="BYTE" Faktor="1" Offset="0"></LogItem>
    <LogItem ID="55" Titel="IK_F.abEmcyMessagesCAN1_5_5             IK_F_T;" Name="IK_F.abEmcyMessagesCAN1_5_5" POU="" Einheit="BYTE" Faktor="1" Offset="0"></LogItem>
    <LogItem ID="56" Titel="IK_F.abEmcyMessagesCAN1_5_6             IK_F_T;" Name="IK_F.abEmcyMessagesCAN1_5_6" POU="" Einheit="BYTE" Faktor="1" Offset="0"></LogItem>
    <LogItem ID="57" Titel="IK_F.abEmcyMessagesCAN1_5_7             IK_F_T;" Name="IK_F.abEmcyMessagesCAN1_5_7" POU="" Einheit="BYTE" Faktor="1" Offset="0"></LogItem>
    <LogItem ID="58" Titel="IK_F.abEmcyMessagesCAN1_6_0             IK_F_T;" Name="IK_F.abEmcyMessagesCAN1_6_0" POU="" Einheit="BYTE" Faktor="1" Offset="0"></LogItem>
    <LogItem ID="59" Titel="IK_F.abEmcyMessagesCAN1_6_1             IK_F_T;" Name="IK_F.abEmcyMessagesCAN1_6_1" POU="" Einheit="BYTE" Faktor="1" Offset="0"></LogItem>
    <LogItem ID="60" Titel="IK_F.abEmcyMessagesCAN1_6_2             IK_F_T;" Name="IK_F.abEmcyMessagesCAN1_6_2" POU="" Einheit="BYTE" Faktor="1" Offset="0"></LogItem>
    <LogItem ID="61" Titel="IK_F.abEmcyMessagesCAN1_6_3             IK_F_T;" Name="IK_F.abEmcyMessagesCAN1_6_3" POU="" Einheit="BYTE" Faktor="1" Offset="0"></LogItem>
    <LogItem ID="62" Titel="IK_F.abEmcyMessagesCAN1_6_4             IK_F_T;" Name="IK_F.abEmcyMessagesCAN1_6_4" POU="" Einheit="BYTE" Faktor="1" Offset="0"></LogItem>
    <LogItem ID="63" Titel="IK_F.abEmcyMessagesCAN1_6_5             IK_F_T;" Name="IK_F.abEmcyMessagesCAN1_6_5" POU="" Einheit="BYTE" Faktor="1" Offset="0"></LogItem>
    <LogItem ID="64" Titel="IK_F.abEmcyMessagesCAN1_6_6             IK_F_T;" Name="IK_F.abEmcyMessagesCAN1_6_6" POU="" Einheit="BYTE" Faktor="1" Offset="0"></LogItem>
    <LogItem ID="65" Titel="IK_F.abEmcyMessagesCAN1_6_7             IK_F_T;" Name="IK_F.abEmcyMessagesCAN1_6_7" POU="" Einheit="BYTE" Faktor="1" Offset="0"></LogItem>
    <LogItem ID="66" Titel="IK_F.abEmcyMessagesCAN1_7_0             IK_F_T;" Name="IK_F.abEmcyMessagesCAN1_7_0" POU="" Einheit="BYTE" Faktor="1" Offset="0"></LogItem>
    <LogItem ID="67" Titel="IK_F.abEmcyMessagesCAN1_7_1             IK_F_T;" Name="IK_F.abEmcyMessagesCAN1_7_1" POU="" Einheit="BYTE" Faktor="1" Offset="0"></LogItem>
    <LogItem ID="68" Titel="IK_F.abEmcyMessagesCAN1_7_2             IK_F_T;" Name="IK_F.abEmcyMessagesCAN1_7_2" POU="" Einheit="BYTE" Faktor="1" Offset="0"></LogItem>
    <LogItem ID="69" Titel="IK_F.abEmcyMessagesCAN1_7_3             IK_F_T;" Name="IK_F.abEmcyMessagesCAN1_7_3" POU="" Einheit="BYTE" Faktor="1" Offset="0"></LogItem>
    <LogItem ID="70" Titel="IK_F.abEmcyMessagesCAN1_7_4             IK_F_T;" Name="IK_F.abEmcyMessagesCAN1_7_4" POU="" Einheit="BYTE" Faktor="1" Offset="0"></LogItem>
    <LogItem ID="71" Titel="IK_F.abEmcyMessagesCAN1_7_5             IK_F_T;" Name="IK_F.abEmcyMessagesCAN1_7_5" POU="" Einheit="BYTE" Faktor="1" Offset="0"></LogItem>
    <LogItem ID="72" Titel="IK_F.abEmcyMessagesCAN1_7_6             IK_F_T;" Name="IK_F.abEmcyMessagesCAN1_7_6" POU="" Einheit="BYTE" Faktor="1" Offset="0"></LogItem>
    <LogItem ID="73" Titel="IK_F.abEmcyMessagesCAN1_7_7             IK_F_T;" Name="IK_F.abEmcyMessagesCAN1_7_7" POU="" Einheit="BYTE" Faktor="1" Offset="0"></LogItem>
    <LogItem ID="74" Titel="IK_F.abEmcyMessagesCAN1_8_0             IK_F_T;" Name="IK_F.abEmcyMessagesCAN1_8_0" POU="" Einheit="BYTE" Faktor="1" Offset="0"></LogItem>
    <LogItem ID="75" Titel="IK_F.abEmcyMessagesCAN1_8_1             IK_F_T;" Name="IK_F.abEmcyMessagesCAN1_8_1" POU="" Einheit="BYTE" Faktor="1" Offset="0"></LogItem>
    <LogItem ID="76" Titel="IK_F.abEmcyMessagesCAN1_8_2             IK_F_T;" Name="IK_F.abEmcyMessagesCAN1_8_2" POU="" Einheit="BYTE" Faktor="1" Offset="0"></LogItem>
    <LogItem ID="77" Titel="IK_F.abEmcyMessagesCAN1_8_3             IK_F_T;" Name="IK_F.abEmcyMessagesCAN1_8_3" POU="" Einheit="BYTE" Faktor="1" Offset="0"></LogItem>
    <LogItem ID="78" Titel="IK_F.abEmcyMessagesCAN1_8_4             IK_F_T;" Name="IK_F.abEmcyMessagesCAN1_8_4" POU="" Einheit="BYTE" Faktor="1" Offset="0"></LogItem>
    <LogItem ID="79" Titel="IK_F.abEmcyMessagesCAN1_8_5             IK_F_T;" Name="IK_F.abEmcyMessagesCAN1_8_5" POU="" Einheit="BYTE" Faktor="1" Offset="0"></LogItem>
    <LogItem ID="80" Titel="IK_F.abEmcyMessagesCAN1_8_6             IK_F_T;" Name="IK_F.abEmcyMessagesCAN1_8_6" POU="" Einheit="BYTE" Faktor="1" Offset="0"></LogItem>
    <LogItem ID="81" Titel="IK_F.abEmcyMessagesCAN1_8_7             IK_F_T;" Name="IK_F.abEmcyMessagesCAN1_8_7" POU="" Einheit="BYTE" Faktor="1" Offset="0"></LogItem>
    <LogItem ID="82" Titel="IK_F.abEmcyMessagesCAN1_9_0             IK_F_T;" Name="IK_F.abEmcyMessagesCAN1_9_0" POU="" Einheit="BYTE" Faktor="1" Offset="0"></LogItem>
    <LogItem ID="83" Titel="IK_F.abEmcyMessagesCAN1_9_1             IK_F_T;" Name="IK_F.abEmcyMessagesCAN1_9_1" POU="" Einheit="BYTE" Faktor="1" Offset="0"></LogItem>
    <LogItem ID="84" Titel="IK_F.abEmcyMessagesCAN1_9_2             IK_F_T;" Name="IK_F.abEmcyMessagesCAN1_9_2" POU="" Einheit="BYTE" Faktor="1" Offset="0"></LogItem>
    <LogItem ID="85" Titel="IK_F.abEmcyMessagesCAN1_9_3             IK_F_T;" Name="IK_F.abEmcyMessagesCAN1_9_3" POU="" Einheit="BYTE" Faktor="1" Offset="0"></LogItem>
    <LogItem ID="86" Titel="IK_F.abEmcyMessagesCAN1_9_4             IK_F_T;" Name="IK_F.abEmcyMessagesCAN1_9_4" POU="" Einheit="BYTE" Faktor="1" Offset="0"></LogItem>
    <LogItem ID="87" Titel="IK_F.abEmcyMessagesCAN1_9_5             IK_F_T;" Name="IK_F.abEmcyMessagesCAN1_9_5" POU="" Einheit="BYTE" Faktor="1" Offset="0"></LogItem>
    <LogItem ID="88" Titel="IK_F.abEmcyMessagesCAN1_9_6             IK_F_T;" Name="IK_F.abEmcyMessagesCAN1_9_6" POU="" Einheit="BYTE" Faktor="1" Offset="0"></LogItem>
    <LogItem ID="89" Titel="IK_F.abEmcyMessagesCAN1_9_7             IK_F_T;" Name="IK_F.abEmcyMessagesCAN1_9_7" POU="" Einheit="BYTE" Faktor="1" Offset="0"></LogItem>
    <LogItem ID="90" Titel="IK_F.uiNbrEmcyMessagesCAN1              IK_F_T;" Name="IK_F.uiNbrEmcyMessagesCAN1" POU="" Einheit="UINT" Faktor="1" Offset="0"></LogItem>
    <LogItem ID="91" Titel="IK_F.auiEmcyNodesCAN2_0                 IK_F_T;" Name="IK_F.auiEmcyNodesCAN2_0" POU="" Einheit="UINT" Faktor="1" Offset="0"></LogItem>
    <LogItem ID="92" Titel="IK_F.auiEmcyNodesCAN2_1                 IK_F_T;" Name="IK_F.auiEmcyNodesCAN2_1" POU="" Einheit="UINT" Faktor="1" Offset="0"></LogItem>
    <LogItem ID="93" Titel="IK_F.auiEmcyNodesCAN2_2                 IK_F_T;" Name="IK_F.auiEmcyNodesCAN2_2" POU="" Einheit="UINT" Faktor="1" Offset="0"></LogItem>
    <LogItem ID="94" Titel="IK_F.auiEmcyNodesCAN2_3                 IK_F_T;" Name="IK_F.auiEmcyNodesCAN2_3" POU="" Einheit="UINT" Faktor="1" Offset="0"></LogItem>
    <LogItem ID="95" Titel="IK_F.auiEmcyNodesCAN2_4                 IK_F_T;" Name="IK_F.auiEmcyNodesCAN2_4" POU="" Einheit="UINT" Faktor="1" Offset="0"></LogItem>
    <LogItem ID="96" Titel="IK_F.auiEmcyNodesCAN2_5                 IK_F_T;" Name="IK_F.auiEmcyNodesCAN2_5" POU="" Einheit="UINT" Faktor="1" Offset="0"></LogItem>
    <LogItem ID="97" Titel="IK_F.auiEmcyNodesCAN2_6                 IK_F_T;" Name="IK_F.auiEmcyNodesCAN2_6" POU="" Einheit="UINT" Faktor="1" Offset="0"></LogItem>
    <LogItem ID="98" Titel="IK_F.auiEmcyNodesCAN2_7                 IK_F_T;" Name="IK_F.auiEmcyNodesCAN2_7" POU="" Einheit="UINT" Faktor="1" Offset="0"></LogItem>
    <LogItem ID="99" Titel="IK_F.auiEmcyNodesCAN2_8                 IK_F_T;" Name="IK_F.auiEmcyNodesCAN2_8" POU="" Einheit="UINT" Faktor="1" Offset="0"></LogItem>
    <LogItem ID="100" Titel="IK_F.auiEmcyNodesCAN2_9                 IK_F_T;" Name="IK_F.auiEmcyNodesCAN2_9" POU="" Einheit="UINT" Faktor="1" Offset="0"></LogItem>
    <LogItem ID="101" Titel="IK_F.abEmcyMessagesCAN2_0_0             IK_F_T;" Name="IK_F.abEmcyMessagesCAN2_0_0" POU="" Einheit="BYTE" Faktor="1" Offset="0"></LogItem>
    <LogItem ID="102" Titel="IK_F.abEmcyMessagesCAN2_0_1             IK_F_T;" Name="IK_F.abEmcyMessagesCAN2_0_1" POU="" Einheit="BYTE" Faktor="1" Offset="0"></LogItem>
    <LogItem ID="103" Titel="IK_F.abEmcyMessagesCAN2_0_2             IK_F_T;" Name="IK_F.abEmcyMessagesCAN2_0_2" POU="" Einheit="BYTE" Faktor="1" Offset="0"></LogItem>
    <LogItem ID="104" Titel="IK_F.abEmcyMessagesCAN2_0_3             IK_F_T;" Name="IK_F.abEmcyMessagesCAN2_0_3" POU="" Einheit="BYTE" Faktor="1" Offset="0"></LogItem>
    <LogItem ID="105" Titel="IK_F.abEmcyMessagesCAN2_0_4             IK_F_T;" Name="IK_F.abEmcyMessagesCAN2_0_4" POU="" Einheit="BYTE" Faktor="1" Offset="0"></LogItem>
    <LogItem ID="106" Titel="IK_F.abEmcyMessagesCAN2_0_5             IK_F_T;" Name="IK_F.abEmcyMessagesCAN2_0_5" POU="" Einheit="BYTE" Faktor="1" Offset="0"></LogItem>
    <LogItem ID="107" Titel="IK_F.abEmcyMessagesCAN2_0_6             IK_F_T;" Name="IK_F.abEmcyMessagesCAN2_0_6" POU="" Einheit="BYTE" Faktor="1" Offset="0"></LogItem>
    <LogItem ID="108" Titel="IK_F.abEmcyMessagesCAN2_0_7             IK_F_T;" Name="IK_F.abEmcyMessagesCAN2_0_7" POU="" Einheit="BYTE" Faktor="1" Offset="0"></LogItem>
    <LogItem ID="109" Titel="IK_F.abEmcyMessagesCAN2_1_0             IK_F_T;" Name="IK_F.abEmcyMessagesCAN2_1_0" POU="" Einheit="BYTE" Faktor="1" Offset="0"></LogItem>
    <LogItem ID="110" Titel="IK_F.abEmcyMessagesCAN2_1_1             IK_F_T;" Name="IK_F.abEmcyMessagesCAN2_1_1" POU="" Einheit="BYTE" Faktor="1" Offset="0"></LogItem>
    <LogItem ID="111" Titel="IK_F.abEmcyMessagesCAN2_1_2             IK_F_T;" Name="IK_F.abEmcyMessagesCAN2_1_2" POU="" Einheit="BYTE" Faktor="1" Offset="0"></LogItem>
    <LogItem ID="112" Titel="IK_F.abEmcyMessagesCAN2_1_3             IK_F_T;" Name="IK_F.abEmcyMessagesCAN2_1_3" POU="" Einheit="BYTE" Faktor="1" Offset="0"></LogItem>
    <LogItem ID="113" Titel="IK_F.abEmcyMessagesCAN2_1_4             IK_F_T;" Name="IK_F.abEmcyMessagesCAN2_1_4" POU="" Einheit="BYTE" Faktor="1" Offset="0"></LogItem>
    <LogItem ID="114" Titel="IK_F.abEmcyMessagesCAN2_1_5             IK_F_T;" Name="IK_F.abEmcyMessagesCAN2_1_5" POU="" Einheit="BYTE" Faktor="1" Offset="0"></LogItem>
    <LogItem ID="115" Titel="IK_F.abEmcyMessagesCAN2_1_6             IK_F_T;" Name="IK_F.abEmcyMessagesCAN2_1_6" POU="" Einheit="BYTE" Faktor="1" Offset="0"></LogItem>
    <LogItem ID="116" Titel="IK_F.abEmcyMessagesCAN2_1_7             IK_F_T;" Name="IK_F.abEmcyMessagesCAN2_1_7" POU="" Einheit="BYTE" Faktor="1" Offset="0"></LogItem>
    <LogItem ID="117" Titel="IK_F.abEmcyMessagesCAN2_2_0             IK_F_T;" Name="IK_F.abEmcyMessagesCAN2_2_0" POU="" Einheit="BYTE" Faktor="1" Offset="0"></LogItem>
    <LogItem ID="118" Titel="IK_F.abEmcyMessagesCAN2_2_1             IK_F_T;" Name="IK_F.abEmcyMessagesCAN2_2_1" POU="" Einheit="BYTE" Faktor="1" Offset="0"></LogItem>
    <LogItem ID="119" Titel="IK_F.abEmcyMessagesCAN2_2_2             IK_F_T;" Name="IK_F.abEmcyMessagesCAN2_2_2" POU="" Einheit="BYTE" Faktor="1" Offset="0"></LogItem>
    <LogItem ID="120" Titel="IK_F.abEmcyMessagesCAN2_2_3             IK_F_T;" Name="IK_F.abEmcyMessagesCAN2_2_3" POU="" Einheit="BYTE" Faktor="1" Offset="0"></LogItem>
    <LogItem ID="121" Titel="IK_F.abEmcyMessagesCAN2_2_4             IK_F_T;" Name="IK_F.abEmcyMessagesCAN2_2_4" POU="" Einheit="BYTE" Faktor="1" Offset="0"></LogItem>
    <LogItem ID="122" Titel="IK_F.abEmcyMessagesCAN2_2_5             IK_F_T;" Name="IK_F.abEmcyMessagesCAN2_2_5" POU="" Einheit="BYTE" Faktor="1" Offset="0"></LogItem>
    <LogItem ID="123" Titel="IK_F.abEmcyMessagesCAN2_2_6             IK_F_T;" Name="IK_F.abEmcyMessagesCAN2_2_6" POU="" Einheit="BYTE" Faktor="1" Offset="0"></LogItem>
    <LogItem ID="124" Titel="IK_F.abEmcyMessagesCAN2_2_7             IK_F_T;" Name="IK_F.abEmcyMessagesCAN2_2_7" POU="" Einheit="BYTE" Faktor="1" Offset="0"></LogItem>
    <LogItem ID="125" Titel="IK_F.abEmcyMessagesCAN2_3_0             IK_F_T;" Name="IK_F.abEmcyMessagesCAN2_3_0" POU="" Einheit="BYTE" Faktor="1" Offset="0"></LogItem>
    <LogItem ID="126" Titel="IK_F.abEmcyMessagesCAN2_3_1             IK_F_T;" Name="IK_F.abEmcyMessagesCAN2_3_1" POU="" Einheit="BYTE" Faktor="1" Offset="0"></LogItem>
    <LogItem ID="127" Titel="IK_F.abEmcyMessagesCAN2_3_2             IK_F_T;" Name="IK_F.abEmcyMessagesCAN2_3_2" POU="" Einheit="BYTE" Faktor="1" Offset="0"></LogItem>
    <LogItem ID="128" Titel="IK_F.abEmcyMessagesCAN2_3_3             IK_F_T;" Name="IK_F.abEmcyMessagesCAN2_3_3" POU="" Einheit="BYTE" Faktor="1" Offset="0"></LogItem>
    <LogItem ID="129" Titel="IK_F.abEmcyMessagesCAN2_3_4             IK_F_T;" Name="IK_F.abEmcyMessagesCAN2_3_4" POU="" Einheit="BYTE" Faktor="1" Offset="0"></LogItem>
    <LogItem ID="130" Titel="IK_F.abEmcyMessagesCAN2_3_5             IK_F_T;" Name="IK_F.abEmcyMessagesCAN2_3_5" POU="" Einheit="BYTE" Faktor="1" Offset="0"></LogItem>
    <LogItem ID="131" Titel="IK_F.abEmcyMessagesCAN2_3_6             IK_F_T;" Name="IK_F.abEmcyMessagesCAN2_3_6" POU="" Einheit="BYTE" Faktor="1" Offset="0"></LogItem>
    <LogItem ID="132" Titel="IK_F.abEmcyMessagesCAN2_3_7             IK_F_T;" Name="IK_F.abEmcyMessagesCAN2_3_7" POU="" Einheit="BYTE" Faktor="1" Offset="0"></LogItem>
    <LogItem ID="133" Titel="IK_F.abEmcyMessagesCAN2_4_0             IK_F_T;" Name="IK_F.abEmcyMessagesCAN2_4_0" POU="" Einheit="BYTE" Faktor="1" Offset="0"></LogItem>
    <LogItem ID="134" Titel="IK_F.abEmcyMessagesCAN2_4_1             IK_F_T;" Name="IK_F.abEmcyMessagesCAN2_4_1" POU="" Einheit="BYTE" Faktor="1" Offset="0"></LogItem>
    <LogItem ID="135" Titel="IK_F.abEmcyMessagesCAN2_4_2             IK_F_T;" Name="IK_F.abEmcyMessagesCAN2_4_2" POU="" Einheit="BYTE" Faktor="1" Offset="0"></LogItem>
    <LogItem ID="136" Titel="IK_F.abEmcyMessagesCAN2_4_3             IK_F_T;" Name="IK_F.abEmcyMessagesCAN2_4_3" POU="" Einheit="BYTE" Faktor="1" Offset="0"></LogItem>
    <LogItem ID="137" Titel="IK_F.abEmcyMessagesCAN2_4_4             IK_F_T;" Name="IK_F.abEmcyMessagesCAN2_4_4" POU="" Einheit="BYTE" Faktor="1" Offset="0"></LogItem>
    <LogItem ID="138" Titel="IK_F.abEmcyMessagesCAN2_4_5             IK_F_T;" Name="IK_F.abEmcyMessagesCAN2_4_5" POU="" Einheit="BYTE" Faktor="1" Offset="0"></LogItem>
    <LogItem ID="139" Titel="IK_F.abEmcyMessagesCAN2_4_6             IK_F_T;" Name="IK_F.abEmcyMessagesCAN2_4_6" POU="" Einheit="BYTE" Faktor="1" Offset="0"></LogItem>
    <LogItem ID="140" Titel="IK_F.abEmcyMessagesCAN2_4_7             IK_F_T;" Name="IK_F.abEmcyMessagesCAN2_4_7" POU="" Einheit="BYTE" Faktor="1" Offset="0"></LogItem>
    <LogItem ID="141" Titel="IK_F.abEmcyMessagesCAN2_5_0             IK_F_T;" Name="IK_F.abEmcyMessagesCAN2_5_0" POU="" Einheit="BYTE" Faktor="1" Offset="0"></LogItem>
    <LogItem ID="142" Titel="IK_F.abEmcyMessagesCAN2_5_1             IK_F_T;" Name="IK_F.abEmcyMessagesCAN2_5_1" POU="" Einheit="BYTE" Faktor="1" Offset="0"></LogItem>
    <LogItem ID="143" Titel="IK_F.abEmcyMessagesCAN2_5_2             IK_F_T;" Name="IK_F.abEmcyMessagesCAN2_5_2" POU="" Einheit="BYTE" Faktor="1" Offset="0"></LogItem>
    <LogItem ID="144" Titel="IK_F.abEmcyMessagesCAN2_5_3             IK_F_T;" Name="IK_F.abEmcyMessagesCAN2_5_3" POU="" Einheit="BYTE" Faktor="1" Offset="0"></LogItem>
    <LogItem ID="145" Titel="IK_F.abEmcyMessagesCAN2_5_4             IK_F_T;" Name="IK_F.abEmcyMessagesCAN2_5_4" POU="" Einheit="BYTE" Faktor="1" Offset="0"></LogItem>
    <LogItem ID="146" Titel="IK_F.abEmcyMessagesCAN2_5_5             IK_F_T;" Name="IK_F.abEmcyMessagesCAN2_5_5" POU="" Einheit="BYTE" Faktor="1" Offset="0"></LogItem>
    <LogItem ID="147" Titel="IK_F.abEmcyMessagesCAN2_5_6             IK_F_T;" Name="IK_F.abEmcyMessagesCAN2_5_6" POU="" Einheit="BYTE" Faktor="1" Offset="0"></LogItem>
    <LogItem ID="148" Titel="IK_F.abEmcyMessagesCAN2_5_7             IK_F_T;" Name="IK_F.abEmcyMessagesCAN2_5_7" POU="" Einheit="BYTE" Faktor="1" Offset="0"></LogItem>
    <LogItem ID="149" Titel="IK_F.abEmcyMessagesCAN2_6_0             IK_F_T;" Name="IK_F.abEmcyMessagesCAN2_6_0" POU="" Einheit="BYTE" Faktor="1" Offset="0"></LogItem>
    <LogItem ID="150" Titel="IK_F.abEmcyMessagesCAN2_6_1             IK_F_T;" Name="IK_F.abEmcyMessagesCAN2_6_1" POU="" Einheit="BYTE" Faktor="1" Offset="0"></LogItem>
    <LogItem ID="151" Titel="IK_F.abEmcyMessagesCAN2_6_2             IK_F_T;" Name="IK_F.abEmcyMessagesCAN2_6_2" POU="" Einheit="BYTE" Faktor="1" Offset="0"></LogItem>
    <LogItem ID="152" Titel="IK_F.abEmcyMessagesCAN2_6_3             IK_F_T;" Name="IK_F.abEmcyMessagesCAN2_6_3" POU="" Einheit="BYTE" Faktor="1" Offset="0"></LogItem>
    <LogItem ID="153" Titel="IK_F.abEmcyMessagesCAN2_6_4             IK_F_T;" Name="IK_F.abEmcyMessagesCAN2_6_4" POU="" Einheit="BYTE" Faktor="1" Offset="0"></LogItem>
    <LogItem ID="154" Titel="IK_F.abEmcyMessagesCAN2_6_5             IK_F_T;" Name="IK_F.abEmcyMessagesCAN2_6_5" POU="" Einheit="BYTE" Faktor="1" Offset="0"></LogItem>
    <LogItem ID="155" Titel="IK_F.abEmcyMessagesCAN2_6_6             IK_F_T;" Name="IK_F.abEmcyMessagesCAN2_6_6" POU="" Einheit="BYTE" Faktor="1" Offset="0"></LogItem>
    <LogItem ID="156" Titel="IK_F.abEmcyMessagesCAN2_6_7             IK_F_T;" Name="IK_F.abEmcyMessagesCAN2_6_7" POU="" Einheit="BYTE" Faktor="1" Offset="0"></LogItem>
    <LogItem ID="157" Titel="IK_F.abEmcyMessagesCAN2_7_0             IK_F_T;" Name="IK_F.abEmcyMessagesCAN2_7_0" POU="" Einheit="BYTE" Faktor="1" Offset="0"></LogItem>
    <LogItem ID="158" Titel="IK_F.abEmcyMessagesCAN2_7_1             IK_F_T;" Name="IK_F.abEmcyMessagesCAN2_7_1" POU="" Einheit="BYTE" Faktor="1" Offset="0"></LogItem>
    <LogItem ID="159" Titel="IK_F.abEmcyMessagesCAN2_7_2             IK_F_T;" Name="IK_F.abEmcyMessagesCAN2_7_2" POU="" Einheit="BYTE" Faktor="1" Offset="0"></LogItem>
    <LogItem ID="160" Titel="IK_F.abEmcyMessagesCAN2_7_3             IK_F_T;" Name="IK_F.abEmcyMessagesCAN2_7_3" POU="" Einheit="BYTE" Faktor="1" Offset="0"></LogItem>
    <LogItem ID="161" Titel="IK_F.abEmcyMessagesCAN2_7_4             IK_F_T;" Name="IK_F.abEmcyMessagesCAN2_7_4" POU="" Einheit="BYTE" Faktor="1" Offset="0"></LogItem>
    <LogItem ID="162" Titel="IK_F.abEmcyMessagesCAN2_7_5             IK_F_T;" Name="IK_F.abEmcyMessagesCAN2_7_5" POU="" Einheit="BYTE" Faktor="1" Offset="0"></LogItem>
    <LogItem ID="163" Titel="IK_F.abEmcyMessagesCAN2_7_6             IK_F_T;" Name="IK_F.abEmcyMessagesCAN2_7_6" POU="" Einheit="BYTE" Faktor="1" Offset="0"></LogItem>
    <LogItem ID="164" Titel="IK_F.abEmcyMessagesCAN2_7_7             IK_F_T;" Name="IK_F.abEmcyMessagesCAN2_7_7" POU="" Einheit="BYTE" Faktor="1" Offset="0"></LogItem>
    <LogItem ID="165" Titel="IK_F.abEmcyMessagesCAN2_8_0             IK_F_T;" Name="IK_F.abEmcyMessagesCAN2_8_0" POU="" Einheit="BYTE" Faktor="1" Offset="0"></LogItem>
    <LogItem ID="166" Titel="IK_F.abEmcyMessagesCAN2_8_1             IK_F_T;" Name="IK_F.abEmcyMessagesCAN2_8_1" POU="" Einheit="BYTE" Faktor="1" Offset="0"></LogItem>
    <LogItem ID="167" Titel="IK_F.abEmcyMessagesCAN2_8_2             IK_F_T;" Name="IK_F.abEmcyMessagesCAN2_8_2" POU="" Einheit="BYTE" Faktor="1" Offset="0"></LogItem>
    <LogItem ID="168" Titel="IK_F.abEmcyMessagesCAN2_8_3             IK_F_T;" Name="IK_F.abEmcyMessagesCAN2_8_3" POU="" Einheit="BYTE" Faktor="1" Offset="0"></LogItem>
    <LogItem ID="169" Titel="IK_F.abEmcyMessagesCAN2_8_4             IK_F_T;" Name="IK_F.abEmcyMessagesCAN2_8_4" POU="" Einheit="BYTE" Faktor="1" Offset="0"></LogItem>
    <LogItem ID="170" Titel="IK_F.abEmcyMessagesCAN2_8_5             IK_F_T;" Name="IK_F.abEmcyMessagesCAN2_8_5" POU="" Einheit="BYTE" Faktor="1" Offset="0"></LogItem>
    <LogItem ID="171" Titel="IK_F.abEmcyMessagesCAN2_8_6             IK_F_T;" Name="IK_F.abEmcyMessagesCAN2_8_6" POU="" Einheit="BYTE" Faktor="1" Offset="0"></LogItem>
    <LogItem ID="172" Titel="IK_F.abEmcyMessagesCAN2_8_7             IK_F_T;" Name="IK_F.abEmcyMessagesCAN2_8_7" POU="" Einheit="BYTE" Faktor="1" Offset="0"></LogItem>
    <LogItem ID="173" Titel="IK_F.abEmcyMessagesCAN2_9_0             IK_F_T;" Name="IK_F.abEmcyMessagesCAN2_9_0" POU="" Einheit="BYTE" Faktor="1" Offset="0"></LogItem>
    <LogItem ID="174" Titel="IK_F.abEmcyMessagesCAN2_9_1             IK_F_T;" Name="IK_F.abEmcyMessagesCAN2_9_1" POU="" Einheit="BYTE" Faktor="1" Offset="0"></LogItem>
    <LogItem ID="175" Titel="IK_F.abEmcyMessagesCAN2_9_2             IK_F_T;" Name="IK_F.abEmcyMessagesCAN2_9_2" POU="" Einheit="BYTE" Faktor="1" Offset="0"></LogItem>
    <LogItem ID="176" Titel="IK_F.abEmcyMessagesCAN2_9_3             IK_F_T;" Name="IK_F.abEmcyMessagesCAN2_9_3" POU="" Einheit="BYTE" Faktor="1" Offset="0"></LogItem>
    <LogItem ID="177" Titel="IK_F.abEmcyMessagesCAN2_9_4             IK_F_T;" Name="IK_F.abEmcyMessagesCAN2_9_4" POU="" Einheit="BYTE" Faktor="1" Offset="0"></LogItem>
    <LogItem ID="178" Titel="IK_F.abEmcyMessagesCAN2_9_5             IK_F_T;" Name="IK_F.abEmcyMessagesCAN2_9_5" POU="" Einheit="BYTE" Faktor="1" Offset="0"></LogItem>
    <LogItem ID="179" Titel="IK_F.abEmcyMessagesCAN2_9_6             IK_F_T;" Name="IK_F.abEmcyMessagesCAN2_9_6" POU="" Einheit="BYTE" Faktor="1" Offset="0"></LogItem>
    <LogItem ID="180" Titel="IK_F.abEmcyMessagesCAN2_9_7             IK_F_T;" Name="IK_F.abEmcyMessagesCAN2_9_7" POU="" Einheit="BYTE" Faktor="1" Offset="0"></LogItem>
    <LogItem ID="181" Titel="IK_F.uiNbrEmcyMessagesCAN2              IK_F_T;" Name="IK_F.uiNbrEmcyMessagesCAN2" POU="" Einheit="UINT" Faktor="1" Offset="0"></LogItem>
  </LogResource>
</RailMonitor>
